metabeeai/__init__.py
metabeeai/cli.py
metabeeai/config.py
metabeeai/logging.py
metabeeai/llm_benchmarking/__init__.py
metabeeai/llm_benchmarking/deepeval_benchmarking.py
metabeeai/llm_benchmarking/edge_cases.py
metabeeai/llm_benchmarking/plot_metrics_comparison.py
metabeeai/llm_benchmarking/prep_benchmark_data.py
metabeeai/llm_benchmarking/run_benchmarking.py
metabeeai/llm_review_software/__init__.py
metabeeai/llm_review_software/annotator.py
metabeeai/llm_review_software/beegui.py
metabeeai/metabeeai_llm/__init__.py
metabeeai/metabeeai_llm/json_multistage_qa.py
metabeeai/metabeeai_llm/llm_pipeline.py
metabeeai/metabeeai_llm/pipeline_config.py
metabeeai/metabeeai_llm/questions.yml
metabeeai/process_pdfs/__init__.py
metabeeai/process_pdfs/batch_deduplicate.py
metabeeai/process_pdfs/deduplicate_chunks.py
metabeeai/process_pdfs/merger.py
metabeeai/process_pdfs/process_all.py
metabeeai/process_pdfs/split_pdf.py
metabeeai/process_pdfs/va_process_papers.py
metabeeai/query_database/investigate_additional_stressors.py
metabeeai/query_database/investigate_bee_species.py
metabeeai/query_database/investigate_pesticides.py
metabeeai/query_database/investigate_significance.py
metabeeai/query_database/network_analysis.py
metabeeai/query_database/trend_analysis.py
metabeeai-0.2.0.dist-info/licenses/LICENSE
metabeeai-0.2.0.dist-info/METADATA
metabeeai-0.2.0.dist-info/WHEEL
metabeeai-0.2.0.dist-info/entry_points.txt
metabeeai-0.2.0.dist-info/top_level.txt
metabeeai-0.2.0.dist-info/RECORD
