Metadata-Version: 2.4
Name: metabeeai
Version: 0.2.0
Summary: MetaBeeAI LLM Pipeline for PDF processing and data extraction
Author-email: Rachel Parkinson <rachel.parkinson@biology.ox.ac.uk>, Alasdair Wilson <alasdair.wilson@dtc.ox.ac.uk>, Shuxiang Cao <shuxiang.cao@physics.ox.ac.uk>, Mikael Mieskolainen <mikael.mieskolainen@cern.ch>
License: BSD-3-Clause
Project-URL: Homepage, https://github.com/MetaBeeAI/MetaBeeAI
Project-URL: Repository, https://github.com/MetaBeeAI/MetaBeeAI
Project-URL: Issues, https://github.com/MetaBeeAI/MetaBeeAI/issues
Keywords: pdf,llm,nlp,data extraction,fastapi,openai
Requires-Python: >=3.11
License-File: LICENSE
Requires-Dist: python-dotenv>=1.0.1
Requires-Dist: openai>=2.0.0
Requires-Dist: litellm>=1.40.0
Requires-Dist: pandas>=2.0.0
Requires-Dist: numpy>=1.26.0
Requires-Dist: PyPDF2>=3.0.1
Requires-Dist: pymupdf>=1.22.0
Requires-Dist: pydantic>=2.9.0
Requires-Dist: PyYAML>=6.0.1
Requires-Dist: PyQt5>=5.15.9
Requires-Dist: termcolor>=2.3.0
Requires-Dist: tqdm>=4.66.1
Requires-Dist: matplotlib>=3.6.0
Requires-Dist: seaborn>=0.13.0
Requires-Dist: networkx>=3.0
Requires-Dist: deepeval>=3.1.0
Requires-Dist: requests>=2.31.0
Provides-Extra: dev
Requires-Dist: pytest>=7.4.0; extra == "dev"
Requires-Dist: ruff>=0.1.0; extra == "dev"
Requires-Dist: mypy>=1.8.0; extra == "dev"
Provides-Extra: docs
Requires-Dist: sphinx>=7.0.1; extra == "docs"
Requires-Dist: pydata-sphinx-theme>=0.15.2; extra == "docs"
Requires-Dist: sphinx-autodoc-typehints>=1.24.0; extra == "docs"
Requires-Dist: sphinx-gallery>=0.15.0; extra == "docs"
Requires-Dist: sphinx-automodapi>=0.16.0; extra == "docs"
Requires-Dist: myst-parser>=2.0.0; extra == "docs"
Dynamic: license-file
